Workbook

Sheet Governance_Interactions
A1: Interaction_ID | B1: Measure_ID | C1: WTO_Document | D1: WTO_Forum | E1: Participant | F1: Measure | G1: Measure_Owner | H1: Engagement_Function | I1: Governance_Dimension_1 | J1: Governance_Topic_1 | K1: Governance_Dimension_2 | L1: Governance_Topic_2 | M1: Governance_Dimension_3 | N1: Governance_Topic_3 | O1: Governance_Dimension_4 | P1: Governance_Topic_4 | Q1: Governance_Dimension_5 | R1: Governance_Topic_5 | S1: Reference_Page | T1: Reference_Paragraph | U1: Confidence | V1: Interaction_Summary
A2: GI-001 | B2: =_xlfn.XLOOKUP(F2,Measure_Register!B:B,Measure_Register!A:A,"NA",0,1) -> M001 | C2: WT/CTE/GEN/37/Rev.1 | D2: CTE | E2: European Union | F2: Carbon Border Adjustment Mechanism (CBAM) | G2: European Union | H2: Regulatory Update | I2: Regulatory | J2: Regulatory Architecture | K2: Regulatory | L2: Scope Expansion | M2: Technical | N2: MRV | O2: Technical | P2: Verification Framework | Q2: Institutional | R2: Stakeholder Consultation | S2: 1-2 | T2: 2-7 | U2: 100 | V2: CBAM revision package, scope expansion and implementation roadmap.
A3: GI-002 | B3: =_xlfn.XLOOKUP(F3,Measure_Register!B:B,Measure_Register!A:A,"NA",0,1) -> M001 | C3: WT/CTE/GEN/37/Rev.1 | D3: CTE | E3: European Union | F3: Carbon Border Adjustment Mechanism (CBAM) | G3: European Union | H3: Implementation Guidance | I3: Technical | J3: Carbon Accounting | K3: Technical | L3: Default Values | M3: Regulatory | N3: Accreditation | O3: Regulatory | P3: Mutual Recognition | Q3: Institutional | R3: Implementation Framework | S3: 2 | T3: 7 | U3: 100 | V3: Detailed implementing acts covering methodologies, accreditation and registry design.
A4: GI-003 | B4: =_xlfn.XLOOKUP(F4,Measure_Register!B:B,Measure_Register!A:A,"NA",0,1) -> M002 | C4: WT/CTE/GEN/41 | D4: CTE | E4: European Union | F4: CBAM Carbon Price Deduction Rules | G4: European Union | H4: Consultation Announcement | I4: Regulatory | J4: Recognition of Foreign Carbon Pricing Systems | K4: Technical | L4: Evidence Requirements | M4: Institutional | N4: Public Consultation | O4: Regulatory | P4: Carbon Price Deduction | Q4: Institutional | R4: Transparency | S4: 1 | T4: 2-6 | U4: 100 | V4: Consultation on deduction of carbon prices paid in third countries.
A5: GI-004 | B5: =_xlfn.XLOOKUP(F5,Measure_Register!B:B,Measure_Register!A:A,"NA",0,1) -> M001 | C5: G/C/M/153 | D5: CTG | E5: Argentina | F5: Carbon Border Adjustment Mechanism (CBAM) | G5: European Union | H5: Concern Raising | I5: Legal | J5: WTO Consistency | K5: Development | L5: CBDR | M5: Economic | N5: Competitiveness | O5: Regulatory | P5: Interoperability | S5: 59-65 | T5: 10.3.14 | U5: 90 | V5: CBAM concerns raised in CTG.
A6: GI-005 | B6: =_xlfn.XLOOKUP(F6,Measure_Register!B:B,Measure_Register!A:A,"NA",0,1) -> M001 | C6: G/C/M/153 | D6: CTG | E6: Brazil | F6: Carbon Border Adjustment Mechanism (CBAM) | G6: European Union | H6: Concern Raising | I6: Technical | J6: MRV | K6: Regulatory | L6: Interoperability | M6: Economic | N6: Compliance Costs | O6: Development | P6: Capacity Constraints | S6: 59-65 | T6: 10.3.14 | U6: 90 | V6: CBAM implementation and methodology concerns.
A7: GI-006 | B7: =_xlfn.XLOOKUP(F7,Measure_Register!B:B,Measure_Register!A:A,"NA",0,1) -> M001 | C7: G/C/M/153 | D7: CTG | E7: China | F7: Carbon Border Adjustment Mechanism (CBAM) | G7: European Union | H7: Clarification Request | I7: Legal | J7: Non-Discrimination | K7: Technical | L7: Methodology | M7: Technical | N7: Default Values | O7: Regulatory | P7: Transparency | S7: 59-65 | T7: 10.3.14 | U7: 95 | V7: Requested clarification on methodology.
A8: GI-007 | B8: =_xlfn.XLOOKUP(F8,Measure_Register!B:B,Measure_Register!A:A,"NA",0,1) -> M001 | C8: G/C/M/153 | D8: CTG | E8: India | F8: Carbon Border Adjustment Mechanism (CBAM) | G8: European Union | H8: Legal Challenge | I8: Legal | J8: Extraterritoriality | K8: Legal | L8: WTO Consistency | M8: Development | N8: CBDR | O8: Economic | P8: Competitiveness | Q8: Regulatory | R8: Recognition of Foreign Systems | S8: 59-65 | T8: 10.3.14 | U8: 95 | V8: Raised concerns regarding unilateral effects of CBAM.
A9: GI-008 | B9: =_xlfn.XLOOKUP(F9,Measure_Register!B:B,Measure_Register!A:A,"NA",0,1) -> M003 | C9: G/C/M/153 | D9: CTG | E9: Australia | F9: EU Deforestation Regulation (EUDR) | G9: European Union | H9: Concern Raising | I9: Economic | J9: Compliance Costs | K9: Regulatory | L9: Regulatory Coherence | M9: Technical | N9: Traceability | O9: Development | P9: Capacity Constraints | S9: 65-73 | T9: 10.3.15 | U9: 95 | V9: Concerns regarding EUDR implementation.
A10: GI-009 | B10: =_xlfn.XLOOKUP(F10,Measure_Register!B:B,Measure_Register!A:A,"NA",0,1) -> M003 | C10: G/C/M/153 | D10: CTG | E10: European Union | F10: EU Deforestation Regulation (EUDR) | G10: European Union | H10: Regulatory Explanation | I10: Institutional | J10: Implementation Challenges | K10: Regulatory | L10: Regulatory Coherence | M10: Technical | N10: Traceability | S10: 65-73 | T10: 10.3.15 | U10: 95 | V10: Response and explanation concerning EUDR.
A11: GI-015 | B11: =_xlfn.XLOOKUP(F11,Measure_Register!B:B,Measure_Register!A:A,"NA",0,1) -> M004 | C11: G/TBT/M/97 | D11: TBT | E11: United States | F11: Türkiye Recycled Plastics Regulation | G11: Türkiye | H11: Clarification Request | I11: Regulatory | J11: Recognition of Foreign Regulatory Systems | K11: Technical | L11: Traceability | M11: Institutional | N11: Transition Periods | O11: Regulatory | P11: Scope Clarification | S11: 6 | T11: 2.3.3 | U11: 95 | V11: Requested clarification and recognition of FDA determinations.
A12: GI-016 | B12: =_xlfn.XLOOKUP(F12,Measure_Register!B:B,Measure_Register!A:A,"NA",0,1) -> M004 | C12: G/TBT/M/97 | D12: TBT | E12: Türkiye | F12: Türkiye Recycled Plastics Regulation | G12: Türkiye | H12: Regulatory Explanation | I12: Regulatory | J12: Regulatory Alignment | K12: Institutional | L12: Consultation Process | M12: Institutional | N12: Transparency | S12: 6-7 | T12: 2.3.3 | U12: 95 | V12: Explained alignment with EU rules and consultation process.
A13: GI-019 | B13: =_xlfn.XLOOKUP(F13,Measure_Register!B:B,Measure_Register!A:A,"NA",0,1) -> M005 | C13: WT/MIN(26)/22/Add.2 | D13: TESSD | E13: TESSD Working Group | F13: Compilation and Mapping of Trade-Related Climate Policies | G13: Multiple Members | H13: Measure Mapping | I13: Institutional | J13: Information Sharing | K13: Regulatory | L13: Carbon Pricing | M13: Regulatory | N13: Border Carbon Adjustments | O13: Technical | P13: Carbon Measurement Standards | Q13: Institutional | R13: Cooperation Framework | S13: 1-2 | T13: 1.1-3.4 | U13: 100 | V13: Compilation and mapping exercise covering trade-related climate measures and cooperation areas.
A14: GI-020 | B14: =_xlfn.XLOOKUP(F14,Measure_Register!B:B,Measure_Register!A:A,"NA",0,1) -> M005 | C14: WT/MIN(26)/22/Add.2 | D14: TESSD | E14: TESSD Working Group | F14: Compilation and Mapping of Trade-Related Climate Policies | G14: Multiple Members | H14: Governance Reporting | I14: Technical | J14: Carbon Measurement Standards | K14: Regulatory | L14: Conformity Assessment | M14: Institutional | N14: Technical Assistance | O14: Regulatory | P14: Certification Schemes | Q14: Institutional | R14: International Cooperation | S14: 18-19 | T14: 3.1-3.4 | U14: 100 | V14: Identifies areas for cooperation including standards convergence, certification and capacity building.
A15: GI-021 | B15: =_xlfn.XLOOKUP(F15,Measure_Register!B:B,Measure_Register!A:A,"NA",0,1) -> M006 | C15: G/TFA/W/143 | D15: TFA | E15: SVE Group | F15: Small Economies Trade Facilitation Work Programme | G15: SVE Group | H15: Cooperation Proposal | I15: Institutional | J15: Information Sharing | K15: Technical | L15: Digital Tools | M15: Technical | N15: Traceability | O15: Institutional | P15: Dedicated Session | Q15: Institutional | R15: Secretariat Coordination | S15: 1-2 | T15: 1.1-4.2 | U15: 100 | V15: Proposal for dedicated session on vulnerabilities, digitalization, transparency and traceability for small economies.
A16: GI-022 | B16: =_xlfn.XLOOKUP(F16,Measure_Register!B:B,Measure_Register!A:A,"NA",0,1) -> M007 | C16: INF/TE/IDP/W/20/Rev.3 | D16: DPP | E16: DPP Coordinators | F16: Ministerial Statement on Plastic Pollution and Sustainable Plastics Trade | G16: DPP Members | H16: Governance Reporting | I16: Technical | J16: Monitoring | K16: Technical | L16: Traceability | M16: Regulatory | N16: Policy Alignment | O16: Institutional | P16: Technical Assistance | Q16: Institutional | R16: International Cooperation | S16: 1-2 | T16: Ministerial Statement | U16: 100 | V16: Shared understandings on plastics trade governance, traceability, policy coherence and capacity building.
A17: GI-023 | B17: =_xlfn.XLOOKUP(F17,Measure_Register!B:B,Measure_Register!A:A,"NA",0,1) -> M007 | C17: INF/TE/IDP/W/20/Rev.3 | D17: DPP | E17: DPP Coordinators | F17: Ministerial Statement on Plastic Pollution and Sustainable Plastics Trade | G17: DPP Members | H17: Information Sharing | I17: Technical | J17: HS Classification Reform | K17: Regulatory | L17: Single Use Plastics Regulation | M17: Technical | N17: Standards | O17: Institutional | P17: Capacity Building | Q17: Institutional | R17: Knowledge Sharing | S17: 1-2 | T17: Technical Outcomes A-E | U17: 100 | V17: Summarizes analytical work and future cooperation on plastics-related trade measures.
A18: GI-025 | B18: =_xlfn.XLOOKUP(F18,Measure_Register!B:B,Measure_Register!A:A,"NA",0,1) -> M008 | C18: IP/C/M/115/Add.1 | D18: TRIPS | E18: India | F18: Biological Diversity Amendment Act 2023 | G18: India | H18: Notification | I18: Legal | J18: Biodiversity Governance | K18: Legal | L18: Access and Benefit Sharing | M18: Institutional | N18: Traditional Knowledge | S18: 7 | T18: 5 | U18: 95 | V18: Notification regarding biodiversity resources and traditional knowledge.
A19: GI-026 | B19: =_xlfn.XLOOKUP(F19,Measure_Register!B:B,Measure_Register!A:A,"NA",0,1) -> M009 | C19: IP/C/M/115/Add.1 | D19: TRIPS | E19: Multiple Members | F19: TRIPS-CBD Relationship | G19: Multiple Members | H19: Governance Discussion | I19: Legal | J19: Biodiversity Governance | K19: Institutional | L19: Traditional Knowledge | M19: Legal | N19: Disclosure Requirements | S19: 18-23 | T19: Agenda 5-6 | U19: 85 | V19: Discussion on biodiversity and traditional knowledge.
A20: GI-027 | B20: =_xlfn.XLOOKUP(F20,Measure_Register!B:B,Measure_Register!A:A,"NA",0,1) -> M010 | C20: S/C/M/164 | D20: CTS | E20: Council for Trade in Services | F20: Green Services Economy and Sustainable Development | G20: Multiple Members | H20: Thematic Session | I20: Economic | J20: Green Services | K20: Institutional | L20: Sustainable Development | M20: Economic | N20: Green Growth | S20: 2-3 | T20: 4.2-4.3 | U20: 100 | V20: Thematic session on Green Services Economy and Sustainable Development.
A21: GI-028 | B21: =_xlfn.XLOOKUP(F21,Measure_Register!B:B,Measure_Register!A:A,"NA",0,1) -> M010 | C21: S/C/M/164 | D21: CTS | E21: United Kingdom | F21: Green Services Economy and Sustainable Development | G21: Multiple Members | H21: Policy Intervention | I21: Economic | J21: Green Services | K21: Regulatory | L21: Standards Fragmentation | M21: Economic | N21: Climate Services | S21: 3 | T21: 4.4-4.6 | U21: 95 | V21: Discussion of opportunities and barriers in green services.
A22: GI-029 | B22: =_xlfn.XLOOKUP(F22,Measure_Register!B:B,Measure_Register!A:A,"NA",0,1) -> M010 | C22: S/C/M/164 | D22: CTS | E22: Bangladesh | F22: Green Services Economy and Sustainable Development | G22: Multiple Members | H22: Policy Intervention | I22: Development | J22: Capacity Building | K22: Economic | L22: Energy Transition | M22: Institutional | N22: WTO Role | S22: 4 | T22: 4.12 | U22: 95 | V22: Development perspective on clean energy transition.
A23: GI-030 | B23: =_xlfn.XLOOKUP(F23,Measure_Register!B:B,Measure_Register!A:A,"NA",0,1) -> M011 | C23: WT/COMTD/SE/13 | D23: CTD | E23: SVE Group | F23: Green Supply Chains for Development | G23: SVE Group | H23: Thematic Session | I23: Economic | J23: Green Supply Chains | K23: Development | L23: Small Economies | M23: Institutional | N23: Knowledge Sharing | S23: 1 | T23: 2.3 | U23: 100 | V23: Green supply chains session for small economies.
A24: GI-031 | B24: =_xlfn.XLOOKUP(F24,Measure_Register!B:B,Measure_Register!A:A,"NA",0,1) -> M012 | C24: WT/COMTD/SE/13 | D24: CTD | E24: Secretariat | F24: Trade and Climate Change in Small Economies | G24: Small Economies | H24: Governance Reporting | I24: Development | J24: Climate Resilience | K24: Economic | L24: Trade and Climate Linkages | M24: Institutional | N24: International Support | S24: 2 | T24: 2.6 | U24: 100 | V24: Report on trade and climate change in small economies.
A25: GI-032 | B25: =_xlfn.XLOOKUP(F25,Measure_Register!B:B,Measure_Register!A:A,"NA",0,1) -> M013 | C25: WT/COMTD/SE/M/52 | D25: CTD-SVE | E25: ACP Group | F25: Small Economies Work Programme | G25: SVE Group | H25: Support Statement | I25: Development | J25: Climate Vulnerability | K25: Development | L25: Small Economies | M25: Institutional | N25: Monitoring of Trade Challenges | S25: 2 | T25: 9 | U25: 100 | V25: ACP Group links climate vulnerability and trade integration challenges facing small economies.
A26: GI-033 | B26: =_xlfn.XLOOKUP(F26,Measure_Register!B:B,Measure_Register!A:A,"NA",0,1) -> M013 | C26: WT/COMTD/SE/M/52 | D26: CTD-SVE | E26: Mauritius | F26: Small Economies Work Programme | G26: SVE Group | H26: Policy Intervention | I26: Development | J26: Climate Vulnerability | K26: Economic | L26: Supply Chain Resilience | M26: Development | N26: Structural Constraints | S26: 3 | T26: 14-15 | U26: 95 | V26: Highlights climatic emergencies and supply-chain vulnerabilities affecting SVEs.
A27: GI-034 | B27: =_xlfn.XLOOKUP(F27,Measure_Register!B:B,Measure_Register!A:A,"NA",0,1) -> M014 | C27: WT/GC/W/986 | D27: General Council | E27: European Union | F27: WTO Reform and Climate-Related Measures | G27: Multiple Members | H27: Reform Proposal | I27: Institutional | J27: WTO Reform | K27: Regulatory | L27: Climate-Related Measures | M27: Institutional | N27: Committee Monitoring | S27: 2-3 | T27: Predictability Section | U27: 100 | V27: EU identifies climate-related measures as a central contemporary trade governance challenge.
A28: GI-035 | B28: =_xlfn.XLOOKUP(F28,Measure_Register!B:B,Measure_Register!A:A,"NA",0,1) -> M014 | C28: WT/GC/W/986 | D28: General Council | E28: European Union | F28: WTO Reform and Climate-Related Measures | G28: Multiple Members | H28: Governance Proposal | I28: Institutional | J28: Transparency | K28: Institutional | L28: Peer Review | M28: Institutional | N28: Committee Dialogue | S28: 3 | T28: Monitoring Functions | U28: 100 | V28: Highlights WTO committees and transparency functions as governance mechanisms.
A29: GI-036 | B29: =_xlfn.XLOOKUP(F29,Measure_Register!B:B,Measure_Register!A:A,"NA",0,1) -> M015 | C29: WT/MIN(26)/8 | D29: Ministerial Conference | E29: ACP Group | F29: Climate-Related Food Security Cooperation | G29: ACP Members | H29: Ministerial Declaration | I29: Development | J29: Climate Resilience | K29: Economic | L29: Food Security | M29: Institutional | N29: Technical Assistance | S29: 3 | T29: 2.4.8 | U29: 100 | V29: Calls for cooperation to address climate-related food security challenges.
... A31: GI-038 | B31: =_xlfn.XLOOKUP(F31,Measure_Register!B:B,Measure_Register!A:A,"NA",0,1) -> M016 | C31: WT/MIN(26)/8 | D31: Ministerial Conference | E31: ACP Group | F31: Sustainable Trade and Investment Integration | G31: ACP Members | H31: Ministerial Declaration | I31: Development | J31: Sustainable Trade | K31: Institutional | L31: Aid for Trade | M31: Development | N31: Capacity Building | S31: 2 | T31: 1.2.4 | U31: 95 | V31: Calls for technical assistance supporting sustainable trade and investment integration.
A32: GI-039 | B32: =_xlfn.XLOOKUP(F32,Measure_Register!B:B,Measure_Register!A:A,"NA",0,1) -> M017 | C32: WT/GC/M/222 | D32: General Council | E32: Director-General/TNC | F32: CTE and TRIPS Special Session Process | G32: Multiple Members | H32: Governance Reporting | I32: Institutional | J32: Climate Governance Negotiations | K32: Institutional | L32: Committee Processes | S32: 11-13 | T32: 2.7(a)-2.13(a) | U32: 90 | V32: Reports status of CTE and TRIPS Special Session negotiations and future work.
A33: GI-040 | B33: =_xlfn.XLOOKUP(F33,Measure_Register!B:B,Measure_Register!A:A,"NA",0,1) -> M019 | C33: WT/TPR/M/480/Add.1 | D33: TPRB | E33: Singapore | F33: Thailand Climate Change Act | G33: Thailand | H33: Clarification Request | I33: Regulatory | J33: Carbon Pricing | K33: Regulatory | L33: ETS | M33: Regulatory | N33: Carbon Tax | O33: Regulatory | P33: Carbon Credits | Q33: Institutional | R33: Climate Governance Framework | S33: 13 | T33: Q25 | U33: 100 | V33: Question regarding Thailand's Climate Change Act and carbon pricing architecture.
A34: GI-041 | B34: =_xlfn.XLOOKUP(F34,Measure_Register!B:B,Measure_Register!A:A,"NA",0,1) -> M019 | C34: WT/TPR/M/480/Add.1 | D34: TPRB | E34: Thailand | F34: Thailand Climate Change Act | G34: Thailand | H34: Regulatory Explanation | I34: Regulatory | J34: Carbon Pricing | K34: Regulatory | L34: ETS | M34: Regulatory | N34: Carbon Tax | O34: Regulatory | P34: Carbon Credits | Q34: Institutional | R34: Climate Legislation | S34: 13 | T34: Q25 Reply | U34: 100 | V34: Thailand explains design of Climate Change Act and climate governance mechanisms.
A35: GI-042 | B35: =_xlfn.XLOOKUP(F35,Measure_Register!B:B,Measure_Register!A:A,"NA",0,1) -> M020 | C35: WT/TPR/M/480/Add.1 | D35: TPRB | E35: Thailand | F35: EU and UK CBAM/ETS Influence | G35: European Union / United Kingdom | H35: Policy Learning | I35: Regulatory | J35: Border Carbon Adjustment | K35: Regulatory | L35: Interoperability | M35: Institutional | N35: Policy Diffusion | O35: Institutional | P35: Regulatory Learning | Q35: Development | R35: Domestic Adaptation | S35: 13 | T35: Q25 Reply | U35: 100 | V35: Thailand studying EU and UK CBAM and ETS experiences for domestic implementation.
A36: GI-043 | B36: =_xlfn.XLOOKUP(F36,Measure_Register!B:B,Measure_Register!A:A,"NA",0,1) -> M021 | C36: WT/TPR/M/480/Add.1 | D36: TPRB | E36: Singapore | F36: ESG Integration into Trade Policy | G36: Thailand | H36: Clarification Request | I36: Regulatory | J36: ESG Standards | K36: Institutional | L36: Sustainable Development | M36: Institutional | N36: Trade Policy Integration | S36: 8 | T36: Q13 | U36: 95 | V36: Question regarding integration of ESG principles into trade policy.
A37: GI-044 | B37: =_xlfn.XLOOKUP(F37,Measure_Register!B:B,Measure_Register!A:A,"NA",0,1) -> M021 | C37: WT/TPR/M/480/Add.1 | D37: TPRB | E37: Thailand | F37: ESG Integration into Trade Policy | G37: Thailand | H37: Regulatory Explanation | I37: Regulatory | J37: ESG Standards | K37: Institutional | L37: Sustainable Development | M37: Institutional | N37: Trade Facilitation | O37: Institutional | P37: Investment Promotion | Q37: Institutional | R37: Cooperation Initiatives | S37: 8 | T37: Q13 Reply | U37: 95 | V37: Thailand explains sustainability-related considerations in trade policy.
A38: GI-045 | B38: =_xlfn.XLOOKUP(F38,Measure_Register!B:B,Measure_Register!A:A,"NA",0,1) -> M022 | C38: WT/TPR/M/480/Add.1 | D38: TPRB | E38: Singapore | F38: Bonsucro Sustainability Standard | G38: Thailand | H38: Clarification Request | I38: Regulatory | J38: Sustainability Standards | K38: Technical | L38: Certification | M38: Institutional | N38: Bioeconomy Governance | S38: 12 | T38: Q24 | U38: 90 | V38: Question regarding international sustainability standards in bioplastics and bioindustry sectors.
A39: GI-046 | B39: =_xlfn.XLOOKUP(F39,Measure_Register!B:B,Measure_Register!A:A,"NA",0,1) -> M022 | C39: WT/TPR/M/480/Add.1 | D39: TPRB | E39: Thailand | F39: Bonsucro Sustainability Standard | G39: Thailand | H39: Regulatory Explanation | I39: Regulatory | J39: Sustainability Standards | K39: Technical | L39: Certification | M39: Institutional | N39: Bioeconomy Governance | O39: Institutional | P39: International Standards | S39: 12-13 | T39: Q24 Reply | U39: 90 | V39: Thailand references Bonsucro standard for sustainable sugarcane and sugar production.
A40: GI-047 | B40: =_xlfn.XLOOKUP(F40,Measure_Register!B:B,Measure_Register!A:A,"NA",0,1) -> M018 | C40: WT/TPR/M/480/Add.1 | D40: TPRB | E40: Singapore | F40: GMO Labelling Requirements | G40: Thailand | H40: Clarification Request | I40: Technical | J40: Traceability | K40: Regulatory | L40: Consumer Information | S40: 11 | T40: Q20 | U40: 90 | V40: Question on GMO labelling implementation.

Sheet Measure_Register
A1: Measure_ID | B1: Measure_Name | C1: Measure_Owner | D1: Measure_Family | E1: Primary_Sector | F1: Status | G1: First_Document | H1: Description
A2: M001 | B2: Carbon Border Adjustment Mechanism (CBAM) | C2: European Union | D2: Carbon Measures | E2: Multi-sector | F2: In force | G2: WT/CTE/GEN/37/Rev.1 | H2: Carbon border adjustment mechanism.
A3: M002 | B3: CBAM Carbon Price Deduction Rules | C3: European Union | D3: Carbon Measures | E3: Multi-sector | F3: Consultation | G3: WT/CTE/GEN/41 | H3: Rules for deduction of carbon prices paid abroad.
A4: M003 | B4: EU Deforestation Regulation (EUDR) | C4: European Union | D4: Sustainability Regulation | E4: Agriculture/Forestry | F4: In force | G4: G/C/M/153 | H4: Deforestation-free commodities framework.
A5: M004 | B5: Türkiye Recycled Plastics Regulation | C5: Türkiye | D5: Circular Economy Measures | E5: Plastics | F5: Draft | G5: G/TBT/M/97 | H5: Rules for recycled plastics in food contact materials.
A6: M005 | B6: Compilation and Mapping of Trade-Related Climate Policies | C6: Multiple Members | D6: Climate Governance Framework | E6: Multi-sector | F6: Living Document | G6: WT/MIN(26)/22/Add.2 | H6: TESSD mapping and taxonomy of trade-related climate measures.
A7: M006 | B7: Small Economies Trade Facilitation Work Programme | C7: SVE Group | D7: Trade Facilitation Governance | E7: Cross-cutting | F7: Proposal | G7: G/TFA/W/143 | H7: Proposal on transparency, traceability and digital tools.
A8: M007 | B8: Ministerial Statement on Plastic Pollution and Sustainable Plastics Trade | C8: DPP Members | D8: Plastic Pollution Measures | E8: Plastics | F8: Ministerial Outcome | G8: INF/TE/IDP/W/20/Rev.3 | H8: Shared understandings on plastics trade and cooperation.
A9: M008 | B9: Biological Diversity Amendment Act 2023 | C9: India | D9: Biodiversity Measure | E9: Cross-sector | F9: In Force | G9: IP/C/M/115/Add.1 | H9: Biodiversity governance measure
A10: M009 | B10: TRIPS-CBD Relationship | C10: Multiple Members | D10: Biodiversity Governance | E10: Cross-sector | F10: Ongoing | G10: IP/C/M/115/Add.1 | H10: TRIPS and biodiversity discussions
A11: M010 | B11: Green Services Economy and Sustainable Development | C11: Multiple Members | D11: Green Services | E11: Services | F11: Ongoing | G11: S/C/M/164 | H11: CTS thematic discussions
A12: M011 | B12: Green Supply Chains for Development | C12: SVE Group | D12: Sustainable Supply Chains | E12: Cross-sector | F12: Ongoing | G12: WT/COMTD/SE/13 | H12: Green supply chains
... A23: M022 | B23: Bonsucro Sustainability Standard | C23: Thailand | D23: Sustainability Certification | E23: Agriculture/Bioeconomy | F23: Applied Standard | G23: WT/TPR/M/480/Add.1 | H23: Use of Bonsucro sustainability standards in sugar and bioeconomy sectors.
