Workbook

Sheet Master_TrCM_Database
A1: Document | B1: Date | C1: Body | D1: Title | E1: Measure Group | F1: Specific Measure | G1: Country Raising | H1: Tone | I1: Strength | J1: Concern 1 | K1: Concern 2 | L1: Concern 3 | M1: Concern 4 | N1: Concern 5 | O1: Sub-Concern 1 | P1: Sub-Concern 2 | Q1: Sub-Concern 3 | R1: Sub-Concern 4 | S1: Sub-Concern 5
A2: G/C/M/153 | B2: 46085 | C2: CTG | D2: MINUTES OF THE MEETING OF THE COUNCIL FOR TRADE IN GOODS | E2: Carbon Measures | F2: EU CBAM | G2: Brazil | H2: Concerned/Critical | I2: Strong | J2: =_xlfn.XLOOKUP(O2,Sheet1!$B$2:$B$24,Sheet1!$A$2:$A$24,"NA",0,1) -> Development & Equity Concerns | K2: =_xlfn.XLOOKUP(P2,Sheet1!$B$2:$B$24,Sheet1!$A$2:$A$24,"NA",0,1) -> Development & Equity Concerns | L2: =_xlfn.XLOOKUP(Q2,Sheet1!$B$2:$B$24,Sheet1!$A$2:$A$24,"NA",0,1) -> WTO & Legal Concerns | M2: =_xlfn.XLOOKUP(R2,Sheet1!$B$2:$B$24,Sheet1!$A$2:$A$24,"NA",0,1) -> Trade Effects | N2: =_xlfn.XLOOKUP(S2,Sheet1!$B$2:$B$24,Sheet1!$A$2:$A$24,"NA",0,1) -> Implementation & Compliance | O2: S&DT Concerns | P2: Development Impacts | Q2: WTO Compatibility | R2: Discriminatory Effects | S2: Administrative Burden
A3: G/C/M/153 | B3: 46085 | C3: CTG | D3: MINUTES OF THE MEETING OF THE COUNCIL FOR TRADE IN GOODS | E3: Carbon Measures | F3: EU CBAM | G3: China | H3: Concerned/Critical | I3: Strong | J3: =_xlfn.XLOOKUP(O3,Sheet1!$B$2:$B$24,Sheet1!$A$2:$A$24,"NA",0,1) -> WTO & Legal Concerns | K3: =_xlfn.XLOOKUP(P3,Sheet1!$B$2:$B$24,Sheet1!$A$2:$A$24,"NA",0,1) -> WTO & Legal Concerns | L3: =_xlfn.XLOOKUP(Q3,Sheet1!$B$2:$B$24,Sheet1!$A$2:$A$24,"NA",0,1) -> Development & Equity Concerns | M3: =_xlfn.XLOOKUP(R3,Sheet1!$B$2:$B$24,Sheet1!$A$2:$A$24,"NA",0,1) -> Implementation & Compliance | N3: =_xlfn.XLOOKUP(S3,Sheet1!$B$2:$B$24,Sheet1!$A$2:$A$24,"NA",0,1) -> WTO & Legal Concerns | O3: WTO Compatibility | P3: MFN Concerns | Q3: S&DT Concerns | R3: Administrative Burden | S3: Transparency
A4: G/C/M/153 | B4: 46085 | C4: CTG | D4: MINUTES OF THE MEETING OF THE COUNCIL FOR TRADE IN GOODS | E4: Carbon Measures | F4: EU CBAM | G4: Argentina | H4: Concerned/Critical | I4: Strong | J4: =_xlfn.XLOOKUP(O4,Sheet1!$B$2:$B$24,Sheet1!$A$2:$A$24,"NA",0,1) -> WTO & Legal Concerns | K4: =_xlfn.XLOOKUP(P4,Sheet1!$B$2:$B$24,Sheet1!$A$2:$A$24,"NA",0,1) -> Development & Equity Concerns | L4: =_xlfn.XLOOKUP(Q4,Sheet1!$B$2:$B$24,Sheet1!$A$2:$A$24,"NA",0,1) -> Trade Effects | M4: =_xlfn.XLOOKUP(R4,Sheet1!$B$2:$B$24,Sheet1!$A$2:$A$24,"NA",0,1) -> Governance & Regulatory Fragmentation | N4: =_xlfn.XLOOKUP(S4,Sheet1!$B$2:$B$24,Sheet1!$A$2:$A$24,"NA",0,1) -> Regulatory Design & Methodology | O4: WTO Compatibility | P4: S&DT Concerns | Q4: Trade Restrictiveness | R4: Regulatory Fragmentation | S4: Lack of Clarity
A5: G/C/M/153 | B5: 46085 | C5: CTG | D5: MINUTES OF THE MEETING OF THE COUNCIL FOR TRADE IN GOODS | E5: Carbon Measures | F5: EU CBAM | G5: Paraguay | H5: Concerned/Critical | I5: Strong | J5: =_xlfn.XLOOKUP(O5,Sheet1!$B$2:$B$24,Sheet1!$A$2:$A$24,"NA",0,1) -> Development & Equity Concerns | K5: =_xlfn.XLOOKUP(P5,Sheet1!$B$2:$B$24,Sheet1!$A$2:$A$24,"NA",0,1) -> Development & Equity Concerns | L5: =_xlfn.XLOOKUP(Q5,Sheet1!$B$2:$B$24,Sheet1!$A$2:$A$24,"NA",0,1) -> Development & Equity Concerns | M5: =_xlfn.XLOOKUP(R5,Sheet1!$B$2:$B$24,Sheet1!$A$2:$A$24,"NA",0,1) -> Trade Effects | N5: =_xlfn.XLOOKUP(S5,Sheet1!$B$2:$B$24,Sheet1!$A$2:$A$24,"NA",0,1) -> Trade Effects | O5: Development Impacts | P5: Capacity Constraints | Q5: S&DT Concerns | R5: Trade Restrictiveness | S5: Discriminatory Effects
A6: G/C/M/153 | B6: 46085 | C6: CTG | D6: MINUTES OF THE MEETING OF THE COUNCIL FOR TRADE IN GOODS | E6: Carbon Measures | F6: EU CBAM | G6: Indonesia | H6: Concerned/Critical | I6: Strong | J6: =_xlfn.XLOOKUP(O6,Sheet1!$B$2:$B$24,Sheet1!$A$2:$A$24,"NA",0,1) -> WTO & Legal Concerns | K6: =_xlfn.XLOOKUP(P6,Sheet1!$B$2:$B$24,Sheet1!$A$2:$A$24,"NA",0,1) -> Implementation & Compliance | L6: =_xlfn.XLOOKUP(Q6,Sheet1!$B$2:$B$24,Sheet1!$A$2:$A$24,"NA",0,1) -> Regulatory Design & Methodology | M6: =_xlfn.XLOOKUP(R6,Sheet1!$B$2:$B$24,Sheet1!$A$2:$A$24,"NA",0,1) -> WTO & Legal Concerns | N6: =_xlfn.XLOOKUP(S6,Sheet1!$B$2:$B$24,Sheet1!$A$2:$A$24,"NA",0,1) -> Development & Equity Concerns | O6: WTO Compatibility | P6: Administrative Burden | Q6: Carbon Accounting Methodology | R6: Transparency | S6: S&DT Concerns
A7: G/C/M/153 | B7: 46085 | C7: CTG | D7: MINUTES OF THE MEETING OF THE COUNCIL FOR TRADE IN GOODS | E7: Carbon Measures | F7: EU CBAM | G7: Thailand | H7: Mixed | I7: Moderate | J7: =_xlfn.XLOOKUP(O7,Sheet1!$B$2:$B$24,Sheet1!$A$2:$A$24,"NA",0,1) -> Regulatory Design & Methodology | K7: =_xlfn.XLOOKUP(P7,Sheet1!$B$2:$B$24,Sheet1!$A$2:$A$24,"NA",0,1) -> Regulatory Design & Methodology | L7: =_xlfn.XLOOKUP(Q7,Sheet1!$B$2:$B$24,Sheet1!$A$2:$A$24,"NA",0,1) -> Implementation & Compliance | M7: =_xlfn.XLOOKUP(R7,Sheet1!$B$2:$B$24,Sheet1!$A$2:$A$24,"NA",0,1) -> WTO & Legal Concerns | N7: =_xlfn.XLOOKUP(S7,Sheet1!$B$2:$B$24,Sheet1!$A$2:$A$24,"NA",0,1) -> Implementation & Compliance | O7: Carbon Accounting Methodology | P7: Verification Requirements | Q7: Administrative Burden | R7: Transparency | S7: Compliance Costs
A8: G/C/M/153 | B8: 46085 | C8: CTG | D8: MINUTES OF THE MEETING OF THE COUNCIL FOR TRADE IN GOODS | E8: Carbon Measures | F8: EU CBAM | G8: India | H8: Concerned/Critical | I8: Strong | J8: =_xlfn.XLOOKUP(O8,Sheet1!$B$2:$B$24,Sheet1!$A$2:$A$24,"NA",0,1) -> Governance & Regulatory Fragmentation | K8: =_xlfn.XLOOKUP(P8,Sheet1!$B$2:$B$24,Sheet1!$A$2:$A$24,"NA",0,1) -> Governance & Regulatory Fragmentation | L8: =_xlfn.XLOOKUP(Q8,Sheet1!$B$2:$B$24,Sheet1!$A$2:$A$24,"NA",0,1) -> Development & Equity Concerns | M8: =_xlfn.XLOOKUP(R8,Sheet1!$B$2:$B$24,Sheet1!$A$2:$A$24,"NA",0,1) -> Trade Effects | N8: =_xlfn.XLOOKUP(S8,Sheet1!$B$2:$B$24,Sheet1!$A$2:$A$24,"NA",0,1) -> Regulatory Design & Methodology | O8: Extraterritoriality | P8: Regulatory Fragmentation | Q8: S&DT Concerns | R8: Trade Restrictiveness | S8: Lack of Clarity
A9: G/C/M/153 | B9: 46085 | C9: CTG | D9: MINUTES OF THE MEETING OF THE COUNCIL FOR TRADE IN GOODS | E9: Carbon Measures | F9: EU CBAM | G9: Chinese Taipei | H9: Mixed | I9: Moderate | J9: =_xlfn.XLOOKUP(O9,Sheet1!$B$2:$B$24,Sheet1!$A$2:$A$24,"NA",0,1) -> Regulatory Design & Methodology | K9: =_xlfn.XLOOKUP(P9,Sheet1!$B$2:$B$24,Sheet1!$A$2:$A$24,"NA",0,1) -> Regulatory Design & Methodology | L9: =_xlfn.XLOOKUP(Q9,Sheet1!$B$2:$B$24,Sheet1!$A$2:$A$24,"NA",0,1) -> Implementation & Compliance | M9: =_xlfn.XLOOKUP(R9,Sheet1!$B$2:$B$24,Sheet1!$A$2:$A$24,"NA",0,1) -> WTO & Legal Concerns | N9: =_xlfn.XLOOKUP(S9,Sheet1!$B$2:$B$24,Sheet1!$A$2:$A$24,"NA",0,1) -> WTO & Legal Concerns | O9: Carbon Accounting Methodology | P9: Verification Requirements | Q9: Compliance Costs | R9: Transparency | S9: WTO Compatibility
A10: G/C/M/153 | B10: 46085 | C10: CTG | D10: MINUTES OF THE MEETING OF THE COUNCIL FOR TRADE IN GOODS | E10: Carbon Measures | F10: EU CBAM | G10: Türkiye | H10: Concerned/Critical | I10: Strong | J10: =_xlfn.XLOOKUP(O10,Sheet1!$B$2:$B$24,Sheet1!$A$2:$A$24,"NA",0,1) -> Implementation & Compliance | K10: =_xlfn.XLOOKUP(P10,Sheet1!$B$2:$B$24,Sheet1!$A$2:$A$24,"NA",0,1) -> Development & Equity Concerns | L10: =_xlfn.XLOOKUP(Q10,Sheet1!$B$2:$B$24,Sheet1!$A$2:$A$24,"NA",0,1) -> Trade Effects | M10: =_xlfn.XLOOKUP(R10,Sheet1!$B$2:$B$24,Sheet1!$A$2:$A$24,"NA",0,1) -> WTO & Legal Concerns | N10: =_xlfn.XLOOKUP(S10,Sheet1!$B$2:$B$24,Sheet1!$A$2:$A$24,"NA",0,1) -> Regulatory Design & Methodology | O10: Administrative Burden | P10: SME Impacts | Q10: Discriminatory Effects | R10: WTO Compatibility | S10: Lack of Clarity
A11: G/C/M/153 | B11: 46085 | C11: CTG | D11: MINUTES OF THE MEETING OF THE COUNCIL FOR TRADE IN GOODS | E11: Carbon Measures | F11: EU CBAM | G11: Japan | H11: Concerned/Critical | I11: Strong | J11: =_xlfn.XLOOKUP(O11,Sheet1!$B$2:$B$24,Sheet1!$A$2:$A$24,"NA",0,1) -> WTO & Legal Concerns | K11: =_xlfn.XLOOKUP(P11,Sheet1!$B$2:$B$24,Sheet1!$A$2:$A$24,"NA",0,1) -> Regulatory Design & Methodology | L11: =_xlfn.XLOOKUP(Q11,Sheet1!$B$2:$B$24,Sheet1!$A$2:$A$24,"NA",0,1) -> Regulatory Design & Methodology | M11: =_xlfn.XLOOKUP(R11,Sheet1!$B$2:$B$24,Sheet1!$A$2:$A$24,"NA",0,1) -> Implementation & Compliance | N11: =_xlfn.XLOOKUP(S11,Sheet1!$B$2:$B$24,Sheet1!$A$2:$A$24,"NA",0,1) -> Trade Effects | O11: WTO Compatibility | P11: Carbon Accounting Methodology | Q11: Verification Requirements | R11: Compliance Costs | S11: Trade Restrictiveness
A12: G/C/M/153 | B12: 46085 | C12: CTG | D12: MINUTES OF THE MEETING OF THE COUNCIL FOR TRADE IN GOODS | E12: Carbon Measures | F12: EU CBAM | G12: Republic of Korea | H12: Mixed | I12: Moderate | J12: =_xlfn.XLOOKUP(O12,Sheet1!$B$2:$B$24,Sheet1!$A$2:$A$24,"NA",0,1) -> Regulatory Design & Methodology | K12: =_xlfn.XLOOKUP(P12,Sheet1!$B$2:$B$24,Sheet1!$A$2:$A$24,"NA",0,1) -> Regulatory Design & Methodology | L12: =_xlfn.XLOOKUP(Q12,Sheet1!$B$2:$B$24,Sheet1!$A$2:$A$24,"NA",0,1) -> Trade Effects | M12: =_xlfn.XLOOKUP(R12,Sheet1!$B$2:$B$24,Sheet1!$A$2:$A$24,"NA",0,1) -> Implementation & Compliance | N12: =_xlfn.XLOOKUP(S12,Sheet1!$B$2:$B$24,Sheet1!$A$2:$A$24,"NA",0,1) -> Regulatory Design & Methodology | O12: Carbon Accounting Methodology | P12: Verification Requirements | Q12: Discriminatory Effects | R12: Administrative Burden | S12: Lack of Clarity
A13: G/C/M/153 | B13: 46085 | C13: CTG | D13: MINUTES OF THE MEETING OF THE COUNCIL FOR TRADE IN GOODS | E13: Sustainable Food & Agriculture Measures | F13: EUDR | G13: Brazil | H13: Concerned/Critical | I13: Strong | J13: =_xlfn.XLOOKUP(O13,Sheet1!$B$2:$B$24,Sheet1!$A$2:$A$24,"NA",0,1) -> WTO & Legal Concerns | K13: =_xlfn.XLOOKUP(P13,Sheet1!$B$2:$B$24,Sheet1!$A$2:$A$24,"NA",0,1) -> Trade Effects | L13: =_xlfn.XLOOKUP(Q13,Sheet1!$B$2:$B$24,Sheet1!$A$2:$A$24,"NA",0,1) -> Trade Effects | M13: =_xlfn.XLOOKUP(R13,Sheet1!$B$2:$B$24,Sheet1!$A$2:$A$24,"NA",0,1) -> Regulatory Design & Methodology | N13: =_xlfn.XLOOKUP(S13,Sheet1!$B$2:$B$24,Sheet1!$A$2:$A$24,"NA",0,1) -> Implementation & Compliance | O13: WTO Compatibility | P13: Trade Restrictiveness | Q13: Discriminatory Effects | R13: Traceability Requirements | S13: Administrative Burden
... A19: G/C/M/153 | B19: 46085 | C19: CTG | D19: MINUTES OF THE MEETING OF THE COUNCIL FOR TRADE IN GOODS | E19: Sustainable Food & Agriculture Measures | F19: EUDR | G19: Paraguay | H19: Concerned/Critical | I19: Strong | J19: =_xlfn.XLOOKUP(O19,Sheet1!$B$2:$B$24,Sheet1!$A$2:$A$24,"NA",0,1) -> Development & Equity Concerns | K19: =_xlfn.XLOOKUP(P19,Sheet1!$B$2:$B$24,Sheet1!$A$2:$A$24,"NA",0,1) -> Regulatory Design & Methodology | L19: =_xlfn.XLOOKUP(Q19,Sheet1!$B$2:$B$24,Sheet1!$A$2:$A$24,"NA",0,1) -> Implementation & Compliance | M19: =_xlfn.XLOOKUP(R19,Sheet1!$B$2:$B$24,Sheet1!$A$2:$A$24,"NA",0,1) -> Trade Effects | N19: =_xlfn.XLOOKUP(S19,Sheet1!$B$2:$B$24,Sheet1!$A$2:$A$24,"NA",0,1) -> Trade Effects | O19: Development Impacts | P19: Traceability Requirements | Q19: Compliance Costs | R19: Discriminatory Effects | S19: Trade Diversion
A20: G/C/M/153 | B20: 46085 | C20: CTG | D20: MINUTES OF THE MEETING OF THE COUNCIL FOR TRADE IN GOODS | E20: Sustainable Food & Agriculture Measures | F20: EUDR | G20: India | H20: Concerned/Critical | I20: Moderate | J20: =_xlfn.XLOOKUP(O20,Sheet1!$B$2:$B$24,Sheet1!$A$2:$A$24,"NA",0,1) -> Development & Equity Concerns | K20: =_xlfn.XLOOKUP(P20,Sheet1!$B$2:$B$24,Sheet1!$A$2:$A$24,"NA",0,1) -> Governance & Regulatory Fragmentation | L20: =_xlfn.XLOOKUP(Q20,Sheet1!$B$2:$B$24,Sheet1!$A$2:$A$24,"NA",0,1) -> Implementation & Compliance | M20: =_xlfn.XLOOKUP(R20,Sheet1!$B$2:$B$24,Sheet1!$A$2:$A$24,"NA",0,1) -> WTO & Legal Concerns | N20: =_xlfn.XLOOKUP(S20,Sheet1!$B$2:$B$24,Sheet1!$A$2:$A$24,"NA",0,1) -> NA | O20: S&DT Concerns | P20: Extraterritoriality | Q20: Administrative Burden | R20: WTO Compatibility
A21: G/C/M/153 | B21: 46085 | C21: CTG | D21: MINUTES OF THE MEETING OF THE COUNCIL FOR TRADE IN GOODS | E21: Sustainable Food & Agriculture Measures | F21: EUDR | G21: Peru | H21: Concerned/Critical | I21: Strong | J21: =_xlfn.XLOOKUP(O21,Sheet1!$B$2:$B$24,Sheet1!$A$2:$A$24,"NA",0,1) -> WTO & Legal Concerns | K21: =_xlfn.XLOOKUP(P21,Sheet1!$B$2:$B$24,Sheet1!$A$2:$A$24,"NA",0,1) -> Trade Effects | L21: =_xlfn.XLOOKUP(Q21,Sheet1!$B$2:$B$24,Sheet1!$A$2:$A$24,"NA",0,1) -> Regulatory Design & Methodology | M21: =_xlfn.XLOOKUP(R21,Sheet1!$B$2:$B$24,Sheet1!$A$2:$A$24,"NA",0,1) -> Development & Equity Concerns | N21: =_xlfn.XLOOKUP(S21,Sheet1!$B$2:$B$24,Sheet1!$A$2:$A$24,"NA",0,1) -> Implementation & Compliance | O21: WTO Compatibility | P21: Discriminatory Effects | Q21: Traceability Requirements | R21: Development Impacts | S21: Compliance Costs
A22: G/C/M/153 | B22: 46085 | C22: CTG | D22: MINUTES OF THE MEETING OF THE COUNCIL FOR TRADE IN GOODS | E22: Sustainable Food & Agriculture Measures | F22: EUDR | G22: United States | H22: Concerned/Critical | I22: Strong | J22: =_xlfn.XLOOKUP(O22,Sheet1!$B$2:$B$24,Sheet1!$A$2:$A$24,"NA",0,1) -> Trade Effects | K22: =_xlfn.XLOOKUP(P22,Sheet1!$B$2:$B$24,Sheet1!$A$2:$A$24,"NA",0,1) -> Implementation & Compliance | L22: =_xlfn.XLOOKUP(Q22,Sheet1!$B$2:$B$24,Sheet1!$A$2:$A$24,"NA",0,1) -> Regulatory Design & Methodology | M22: =_xlfn.XLOOKUP(R22,Sheet1!$B$2:$B$24,Sheet1!$A$2:$A$24,"NA",0,1) -> Trade Effects | N22: =_xlfn.XLOOKUP(S22,Sheet1!$B$2:$B$24,Sheet1!$A$2:$A$24,"NA",0,1) -> WTO & Legal Concerns | O22: Trade Restrictiveness | P22: Administrative Burden | Q22: Lack of Clarity | R22: Discriminatory Effects | S22: WTO Compatibility
A23: G/C/M/153 | B23: 46085 | C23: CTG | D23: MINUTES OF THE MEETING OF THE COUNCIL FOR TRADE IN GOODS | E23: Sustainable Food & Agriculture Measures | F23: EUDR | G23: Türkiye | H23: Concerned/Critical | I23: Strong | J23: =_xlfn.XLOOKUP(O23,Sheet1!$B$2:$B$24,Sheet1!$A$2:$A$24,"NA",0,1) -> Implementation & Compliance | K23: =_xlfn.XLOOKUP(P23,Sheet1!$B$2:$B$24,Sheet1!$A$2:$A$24,"NA",0,1) -> Implementation & Compliance | L23: =_xlfn.XLOOKUP(Q23,Sheet1!$B$2:$B$24,Sheet1!$A$2:$A$24,"NA",0,1) -> Development & Equity Concerns | M23: =_xlfn.XLOOKUP(R23,Sheet1!$B$2:$B$24,Sheet1!$A$2:$A$24,"NA",0,1) -> Regulatory Design & Methodology | N23: =_xlfn.XLOOKUP(S23,Sheet1!$B$2:$B$24,Sheet1!$A$2:$A$24,"NA",0,1) -> Trade Effects | O23: Administrative Burden | P23: Compliance Costs | Q23: SME Impacts | R23: Lack of Clarity | S23: Trade Restrictiveness
A24: G/C/M/153 | B24: 46085 | C24: CTG | D24: MINUTES OF THE MEETING OF THE COUNCIL FOR TRADE IN GOODS | E24: Sustainable Food & Agriculture Measures | F24: EUDR | G24: Colombia | H24: Concerned/Critical | I24: Strong | J24: =_xlfn.XLOOKUP(O24,Sheet1!$B$2:$B$24,Sheet1!$A$2:$A$24,"NA",0,1) -> Implementation & Compliance | K24: =_xlfn.XLOOKUP(P24,Sheet1!$B$2:$B$24,Sheet1!$A$2:$A$24,"NA",0,1) -> Regulatory Design & Methodology | L24: =_xlfn.XLOOKUP(Q24,Sheet1!$B$2:$B$24,Sheet1!$A$2:$A$24,"NA",0,1) -> Regulatory Design & Methodology | M24: =_xlfn.XLOOKUP(R24,Sheet1!$B$2:$B$24,Sheet1!$A$2:$A$24,"NA",0,1) -> Development & Equity Concerns | N24: =_xlfn.XLOOKUP(S24,Sheet1!$B$2:$B$24,Sheet1!$A$2:$A$24,"NA",0,1) -> Implementation & Compliance | O24: Administrative Burden | P24: Traceability Requirements | Q24: Lack of Clarity | R24: Development Impacts | S24: Compliance Costs
A25: G/C/M/153 | B25: 46085 | C25: CTG | D25: MINUTES OF THE MEETING OF THE COUNCIL FOR TRADE IN GOODS | E25: Sustainable Food & Agriculture Measures | F25: EUDR | G25: New Zealand | H25: Concerned/Critical | I25: Strong | J25: =_xlfn.XLOOKUP(O25,Sheet1!$B$2:$B$24,Sheet1!$A$2:$A$24,"NA",0,1) -> Trade Effects | K25: =_xlfn.XLOOKUP(P25,Sheet1!$B$2:$B$24,Sheet1!$A$2:$A$24,"NA",0,1) -> Trade Effects | L25: =_xlfn.XLOOKUP(Q25,Sheet1!$B$2:$B$24,Sheet1!$A$2:$A$24,"NA",0,1) -> Implementation & Compliance | M25: =_xlfn.XLOOKUP(R25,Sheet1!$B$2:$B$24,Sheet1!$A$2:$A$24,"NA",0,1) -> Implementation & Compliance | N25: =_xlfn.XLOOKUP(S25,Sheet1!$B$2:$B$24,Sheet1!$A$2:$A$24,"NA",0,1) -> WTO & Legal Concerns | O25: Trade Restrictiveness | P25: Discriminatory Effects | Q25: Administrative Burden | R25: Implementation Timeline | S25: WTO Compatibility
A26: G/C/M/153 | B26: 46085 | C26: CTG | D26: MINUTES OF THE MEETING OF THE COUNCIL FOR TRADE IN GOODS | E26: Sustainable Food & Agriculture Measures | F26: EUDR | G26: Australia | H26: Concerned/Critical | I26: Strong | J26: =_xlfn.XLOOKUP(O26,Sheet1!$B$2:$B$24,Sheet1!$A$2:$A$24,"NA",0,1) -> Implementation & Compliance | K26: =_xlfn.XLOOKUP(P26,Sheet1!$B$2:$B$24,Sheet1!$A$2:$A$24,"NA",0,1) -> Implementation & Compliance | L26: =_xlfn.XLOOKUP(Q26,Sheet1!$B$2:$B$24,Sheet1!$A$2:$A$24,"NA",0,1) -> Trade Effects | M26: =_xlfn.XLOOKUP(R26,Sheet1!$B$2:$B$24,Sheet1!$A$2:$A$24,"NA",0,1) -> Regulatory Design & Methodology | N26: =_xlfn.XLOOKUP(S26,Sheet1!$B$2:$B$24,Sheet1!$A$2:$A$24,"NA",0,1) -> Trade Effects | O26: Administrative Burden | P26: Implementation Timeline | Q26: Discriminatory Effects | R26: Lack of Clarity | S26: Trade Restrictiveness
A27: G/C/M/153 | B27: 46085 | C27: CTG | D27: MINUTES OF THE MEETING OF THE COUNCIL FOR TRADE IN GOODS | E27: Carbon Measures | F27: European Green Deal | G27: Russian Federation | H27: Concerned/Critical | I27: Strong | J27: =_xlfn.XLOOKUP(O27,Sheet1!$B$2:$B$24,Sheet1!$A$2:$A$24,"NA",0,1) -> WTO & Legal Concerns | K27: =_xlfn.XLOOKUP(P27,Sheet1!$B$2:$B$24,Sheet1!$A$2:$A$24,"NA",0,1) -> Governance & Regulatory Fragmentation | L27: =_xlfn.XLOOKUP(Q27,Sheet1!$B$2:$B$24,Sheet1!$A$2:$A$24,"NA",0,1) -> Trade Effects | M27: =_xlfn.XLOOKUP(R27,Sheet1!$B$2:$B$24,Sheet1!$A$2:$A$24,"NA",0,1) -> WTO & Legal Concerns | N27: =_xlfn.XLOOKUP(S27,Sheet1!$B$2:$B$24,Sheet1!$A$2:$A$24,"NA",0,1) -> Implementation & Compliance | O27: WTO Compatibility | P27: Regulatory Fragmentation | Q27: Trade Restrictiveness | R27: Unilateral Measures | S27: Administrative Burden
A28: G/C/M/153 | B28: 46085 | C28: CTG | D28: MINUTES OF THE MEETING OF THE COUNCIL FOR TRADE IN GOODS | E28: Sustainable Food & Agriculture Measures | F28: European Green Deal | G28: Russian Federation | H28: Concerned/Critical | I28: Strong | J28: =_xlfn.XLOOKUP(O28,Sheet1!$B$2:$B$24,Sheet1!$A$2:$A$24,"NA",0,1) -> WTO & Legal Concerns | K28: =_xlfn.XLOOKUP(P28,Sheet1!$B$2:$B$24,Sheet1!$A$2:$A$24,"NA",0,1) -> Governance & Regulatory Fragmentation | L28: =_xlfn.XLOOKUP(Q28,Sheet1!$B$2:$B$24,Sheet1!$A$2:$A$24,"NA",0,1) -> Trade Effects | M28: =_xlfn.XLOOKUP(R28,Sheet1!$B$2:$B$24,Sheet1!$A$2:$A$24,"NA",0,1) -> WTO & Legal Concerns | N28: =_xlfn.XLOOKUP(S28,Sheet1!$B$2:$B$24,Sheet1!$A$2:$A$24,"NA",0,1) -> Implementation & Compliance | O28: WTO Compatibility | P28: Regulatory Fragmentation | Q28: Trade Restrictiveness | R28: Unilateral Measures | S28: Administrative Burden
A29: G/C/M/153 | B29: 46085 | C29: CTG | D29: MINUTES OF THE MEETING OF THE COUNCIL FOR TRADE IN GOODS | E29: Carbon Measures | F29: European Green Deal | G29: Russian Federation | H29: Concerned/Critical | I29: Strong | J29: =_xlfn.XLOOKUP(O29,Sheet1!$B$2:$B$24,Sheet1!$A$2:$A$24,"NA",0,1) -> WTO & Legal Concerns | K29: =_xlfn.XLOOKUP(P29,Sheet1!$B$2:$B$24,Sheet1!$A$2:$A$24,"NA",0,1) -> Implementation & Compliance | L29: =_xlfn.XLOOKUP(Q29,Sheet1!$B$2:$B$24,Sheet1!$A$2:$A$24,"NA",0,1) -> Governance & Regulatory Fragmentation | M29: =_xlfn.XLOOKUP(R29,Sheet1!$B$2:$B$24,Sheet1!$A$2:$A$24,"NA",0,1) -> Trade Effects | N29: =_xlfn.XLOOKUP(S29,Sheet1!$B$2:$B$24,Sheet1!$A$2:$A$24,"NA",0,1) -> Regulatory Design & Methodology | O29: WTO Compatibility | P29: Administrative Burden | Q29: Regulatory Fragmentation | R29: Trade Restrictiveness | S29: Lack of Clarity
A30: G/C/M/153 | B30: 46085 | C30: CTG | D30: MINUTES OF THE MEETING OF THE COUNCIL FOR TRADE IN GOODS | E30: Sustainability & Environmental Requirements | F30: European Green Deal | G30: Russian Federation | H30: Concerned/Critical | I30: Strong | J30: =_xlfn.XLOOKUP(O30,Sheet1!$B$2:$B$24,Sheet1!$A$2:$A$24,"NA",0,1) -> Implementation & Compliance | K30: =_xlfn.XLOOKUP(P30,Sheet1!$B$2:$B$24,Sheet1!$A$2:$A$24,"NA",0,1) -> Governance & Regulatory Fragmentation | L30: =_xlfn.XLOOKUP(Q30,Sheet1!$B$2:$B$24,Sheet1!$A$2:$A$24,"NA",0,1) -> Trade Effects | M30: =_xlfn.XLOOKUP(R30,Sheet1!$B$2:$B$24,Sheet1!$A$2:$A$24,"NA",0,1) -> WTO & Legal Concerns | N30: =_xlfn.XLOOKUP(S30,Sheet1!$B$2:$B$24,Sheet1!$A$2:$A$24,"NA",0,1) -> Regulatory Design & Methodology | O30: Administrative Burden | P30: Regulatory Fragmentation | Q30: Trade Restrictiveness | R30: WTO Compatibility | S30: Lack of Clarity
A31: G/C/M/153 | B31: 46085 | C31: CTG | D31: MINUTES OF THE MEETING OF THE COUNCIL FOR TRADE IN GOODS | E31: Due Diligence & Traceability Measures | F31: European Green Deal | G31: Russian Federation | H31: Concerned/Critical | I31: Strong | J31: =_xlfn.XLOOKUP(O31,Sheet1!$B$2:$B$24,Sheet1!$A$2:$A$24,"NA",0,1) -> Implementation & Compliance | K31: =_xlfn.XLOOKUP(P31,Sheet1!$B$2:$B$24,Sheet1!$A$2:$A$24,"NA",0,1) -> Trade Effects | L31: =_xlfn.XLOOKUP(Q31,Sheet1!$B$2:$B$24,Sheet1!$A$2:$A$24,"NA",0,1) -> WTO & Legal Concerns | M31: =_xlfn.XLOOKUP(R31,Sheet1!$B$2:$B$24,Sheet1!$A$2:$A$24,"NA",0,1) -> Governance & Regulatory Fragmentation | N31: =_xlfn.XLOOKUP(S31,Sheet1!$B$2:$B$24,Sheet1!$A$2:$A$24,"NA",0,1) -> Regulatory Design & Methodology | O31: Administrative Burden | P31: Trade Restrictiveness | Q31: WTO Compatibility | R31: Regulatory Fragmentation | S31: Lack of Clarity
A32: G/C/M/153 | B32: 46085 | C32: CTG | D32: MINUTES OF THE MEETING OF THE COUNCIL FOR TRADE IN GOODS | E32: Other TrCMs | F32: European Green Deal | G32: Russian Federation | H32: Concerned/Critical | I32: Strong | J32: =_xlfn.XLOOKUP(O32,Sheet1!$B$2:$B$24,Sheet1!$A$2:$A$24,"NA",0,1) -> WTO & Legal Concerns | K32: =_xlfn.XLOOKUP(P32,Sheet1!$B$2:$B$24,Sheet1!$A$2:$A$24,"NA",0,1) -> Trade Effects | L32: =_xlfn.XLOOKUP(Q32,Sheet1!$B$2:$B$24,Sheet1!$A$2:$A$24,"NA",0,1) -> Governance & Regulatory Fragmentation | M32: =_xlfn.XLOOKUP(R32,Sheet1!$B$2:$B$24,Sheet1!$A$2:$A$24,"NA",0,1) -> Trade Effects | N32: =_xlfn.XLOOKUP(S32,Sheet1!$B$2:$B$24,Sheet1!$A$2:$A$24,"NA",0,1) -> Regulatory Design & Methodology | O32: WTO Compatibility | P32: Trade Restrictiveness | Q32: Regulatory Fragmentation | R32: Discriminatory Effects | S32: Lack of Clarity
... A35: G/C/M/153 | B35: 46085 | C35: CTG | D35: MINUTES OF THE MEETING OF THE COUNCIL FOR TRADE IN GOODS | E35: Other TrCMs | F35: France Revised EV Subsidy Scheme | G35: Republic of Korea | H35: Concerned/Critical | I35: Strong | J35: =_xlfn.XLOOKUP(O35,Sheet1!$B$2:$B$24,Sheet1!$A$2:$A$24,"NA",0,1) -> Trade Effects | K35: =_xlfn.XLOOKUP(P35,Sheet1!$B$2:$B$24,Sheet1!$A$2:$A$24,"NA",0,1) -> WTO & Legal Concerns | L35: =_xlfn.XLOOKUP(Q35,Sheet1!$B$2:$B$24,Sheet1!$A$2:$A$24,"NA",0,1) -> WTO & Legal Concerns | M35: =_xlfn.XLOOKUP(R35,Sheet1!$B$2:$B$24,Sheet1!$A$2:$A$24,"NA",0,1) -> Trade Effects | N35: =_xlfn.XLOOKUP(S35,Sheet1!$B$2:$B$24,Sheet1!$A$2:$A$24,"NA",0,1) -> Regulatory Design & Methodology | O35: Discriminatory Effects | P35: National Treatment | Q35: WTO Compatibility | R35: Export Competitiveness | S35: Carbon Footprint Methodology
A36: G/C/M/153 | B36: 46085 | C36: CTG | D36: MINUTES OF THE MEETING OF THE COUNCIL FOR TRADE IN GOODS | E36: Other TrCMs | F36: France Revised EV Subsidy Scheme | G36: Japan | H36: Concerned/Critical | I36: Moderate | J36: =_xlfn.XLOOKUP(O36,Sheet1!$B$2:$B$24,Sheet1!$A$2:$A$24,"NA",0,1) -> WTO & Legal Concerns | K36: =_xlfn.XLOOKUP(P36,Sheet1!$B$2:$B$24,Sheet1!$A$2:$A$24,"NA",0,1) -> WTO & Legal Concerns | L36: =_xlfn.XLOOKUP(Q36,Sheet1!$B$2:$B$24,Sheet1!$A$2:$A$24,"NA",0,1) -> Trade Effects | M36: =_xlfn.XLOOKUP(R36,Sheet1!$B$2:$B$24,Sheet1!$A$2:$A$24,"NA",0,1) -> NA | N36: =_xlfn.XLOOKUP(S36,Sheet1!$B$2:$B$24,Sheet1!$A$2:$A$24,"NA",0,1) -> NA | O36: National Treatment | P36: WTO Compatibility | Q36: Discriminatory Effects
A37: G/TBT/M/97 | B37: 46031 | C37: TBT | D37: Minutes of the Meeting | E37: Carbon Measures | F37: Carbon Footprint Requirements | G37: China | H37: Recommendation/Request | I37: Moderate | J37: =_xlfn.XLOOKUP(O37,Sheet1!$B$2:$B$24,Sheet1!$A$2:$A$24,"NA",0,1) -> Regulatory Design & Methodology | K37: =_xlfn.XLOOKUP(P37,Sheet1!$B$2:$B$24,Sheet1!$A$2:$A$24,"NA",0,1) -> Implementation & Compliance | L37: =_xlfn.XLOOKUP(Q37,Sheet1!$B$2:$B$24,Sheet1!$A$2:$A$24,"NA",0,1) -> Regulatory Design & Methodology | M37: =_xlfn.XLOOKUP(R37,Sheet1!$B$2:$B$24,Sheet1!$A$2:$A$24,"NA",0,1) -> WTO & Legal Concerns | N37: =_xlfn.XLOOKUP(S37,Sheet1!$B$2:$B$24,Sheet1!$A$2:$A$24,"NA",0,1) -> Implementation & Compliance | O37: Carbon Accounting Methodology | P37: Administrative Burden | Q37: Verification Requirements | R37: Transparency | S37: Compliance Costs
A38: G/TBT/M/97 | B38: 46031 | C38: TBT | D38: Minutes of the Meeting | E38: Carbon Measures | F38: Carbon Footprint Requirements | G38: Russian Federation | H38: Concerned/Critical | I38: Strong | J38: =_xlfn.XLOOKUP(O38,Sheet1!$B$2:$B$24,Sheet1!$A$2:$A$24,"NA",0,1) -> WTO & Legal Concerns | K38: =_xlfn.XLOOKUP(P38,Sheet1!$B$2:$B$24,Sheet1!$A$2:$A$24,"NA",0,1) -> Trade Effects | L38: =_xlfn.XLOOKUP(Q38,Sheet1!$B$2:$B$24,Sheet1!$A$2:$A$24,"NA",0,1) -> Implementation & Compliance | M38: =_xlfn.XLOOKUP(R38,Sheet1!$B$2:$B$24,Sheet1!$A$2:$A$24,"NA",0,1) -> WTO & Legal Concerns | N38: =_xlfn.XLOOKUP(S38,Sheet1!$B$2:$B$24,Sheet1!$A$2:$A$24,"NA",0,1) -> Regulatory Design & Methodology | O38: WTO Compatibility | P38: Trade Restrictiveness | Q38: Administrative Burden | R38: Transparency | S38: Lack of Clarity
A39: G/TBT/M/97 | B39: 46031 | C39: TBT | D39: Minutes of the Meeting | E39: Plastics-Related Measures | F39: Recycled Plastics Requirements | G39: United States | H39: Concerned/Critical | I39: Moderate | J39: =_xlfn.XLOOKUP(O39,Sheet1!$B$2:$B$24,Sheet1!$A$2:$A$24,"NA",0,1) -> Regulatory Design & Methodology | K39: =_xlfn.XLOOKUP(P39,Sheet1!$B$2:$B$24,Sheet1!$A$2:$A$24,"NA",0,1) -> Implementation & Compliance | L39: =_xlfn.XLOOKUP(Q39,Sheet1!$B$2:$B$24,Sheet1!$A$2:$A$24,"NA",0,1) -> Regulatory Design & Methodology | M39: =_xlfn.XLOOKUP(R39,Sheet1!$B$2:$B$24,Sheet1!$A$2:$A$24,"NA",0,1) -> Implementation & Compliance | N39: =_xlfn.XLOOKUP(S39,Sheet1!$B$2:$B$24,Sheet1!$A$2:$A$24,"NA",0,1) -> Implementation & Compliance | O39: Lack of Clarity | P39: Administrative Burden | Q39: Traceability Requirements | R39: Implementation Timeline | S39: Compliance Costs
A40: INF/TE/IDP/W/20/Rev.1 | B40: 46038 | C40: DPP | D40: Draft MC14 Statement | E40: Plastics-Related Measures | F40: Plastic Traceability Requirements | G40: DPP Co-Sponsors | H40: Informative/Neutral | I40: N/A | J40: =_xlfn.XLOOKUP(O40,Sheet1!$B$2:$B$24,Sheet1!$A$2:$A$24,"NA",0,1) -> NA | K40: =_xlfn.XLOOKUP(P40,Sheet1!$B$2:$B$24,Sheet1!$A$2:$A$24,"NA",0,1) -> NA | L40: =_xlfn.XLOOKUP(Q40,Sheet1!$B$2:$B$24,Sheet1!$A$2:$A$24,"NA",0,1) -> NA | M40: =_xlfn.XLOOKUP(R40,Sheet1!$B$2:$B$24,Sheet1!$A$2:$A$24,"NA",0,1) -> NA | N40: =_xlfn.XLOOKUP(S40,Sheet1!$B$2:$B$24,Sheet1!$A$2:$A$24,"NA",0,1) -> NA
A41: INF/TE/IDP/W/20/Rev.1 | B41: 46038 | C41: DPP | D41: Draft MC14 Statement | E41: Plastics-Related Measures | F41: Single-Use Plastics Requirements | G41: DPP Co-Sponsors | H41: Informative/Neutral | I41: N/A | J41: =_xlfn.XLOOKUP(O41,Sheet1!$B$2:$B$24,Sheet1!$A$2:$A$24,"NA",0,1) -> NA | K41: =_xlfn.XLOOKUP(P41,Sheet1!$B$2:$B$24,Sheet1!$A$2:$A$24,"NA",0,1) -> NA | L41: =_xlfn.XLOOKUP(Q41,Sheet1!$B$2:$B$24,Sheet1!$A$2:$A$24,"NA",0,1) -> NA | M41: =_xlfn.XLOOKUP(R41,Sheet1!$B$2:$B$24,Sheet1!$A$2:$A$24,"NA",0,1) -> NA | N41: =_xlfn.XLOOKUP(S41,Sheet1!$B$2:$B$24,Sheet1!$A$2:$A$24,"NA",0,1) -> NA
A42: INF/TE/IDP/W/20/Rev.1 | B42: 46038 | C42: DPP | D42: Draft MC14 Statement | E42: Plastics-Related Measures | F42: Plastics Circular Economy Requirements | G42: DPP Co-Sponsors | H42: Informative/Neutral | I42: N/A | J42: =_xlfn.XLOOKUP(O42,Sheet1!$B$2:$B$24,Sheet1!$A$2:$A$24,"NA",0,1) -> NA | K42: =_xlfn.XLOOKUP(P42,Sheet1!$B$2:$B$24,Sheet1!$A$2:$A$24,"NA",0,1) -> NA | L42: =_xlfn.XLOOKUP(Q42,Sheet1!$B$2:$B$24,Sheet1!$A$2:$A$24,"NA",0,1) -> NA | M42: =_xlfn.XLOOKUP(R42,Sheet1!$B$2:$B$24,Sheet1!$A$2:$A$24,"NA",0,1) -> NA | N42: =_xlfn.XLOOKUP(S42,Sheet1!$B$2:$B$24,Sheet1!$A$2:$A$24,"NA",0,1) -> NA
A43: INF/TE/IDP/W/20/Rev.1 | B43: 46038 | C43: DPP | D43: Draft MC14 Statement | E43: Plastics-Related Measures | F43: Plastics Waste Management Measures | G43: DPP Co-Sponsors | H43: Informative/Neutral | I43: N/A | J43: =_xlfn.XLOOKUP(O43,Sheet1!$B$2:$B$24,Sheet1!$A$2:$A$24,"NA",0,1) -> NA | K43: =_xlfn.XLOOKUP(P43,Sheet1!$B$2:$B$24,Sheet1!$A$2:$A$24,"NA",0,1) -> NA | L43: =_xlfn.XLOOKUP(Q43,Sheet1!$B$2:$B$24,Sheet1!$A$2:$A$24,"NA",0,1) -> NA | M43: =_xlfn.XLOOKUP(R43,Sheet1!$B$2:$B$24,Sheet1!$A$2:$A$24,"NA",0,1) -> NA | N43: =_xlfn.XLOOKUP(S43,Sheet1!$B$2:$B$24,Sheet1!$A$2:$A$24,"NA",0,1) -> NA
A44: INF/TE/IDP/W/20/Rev.1 | B44: 46038 | C44: DPP | D44: Draft MC14 Statement | E44: Plastics-Related Measures | F44: Non-Plastic Substitutes and Alternatives | G44: DPP Co-Sponsors | H44: Informative/Neutral | I44: N/A | J44: =_xlfn.XLOOKUP(O44,Sheet1!$B$2:$B$24,Sheet1!$A$2:$A$24,"NA",0,1) -> NA | K44: =_xlfn.XLOOKUP(P44,Sheet1!$B$2:$B$24,Sheet1!$A$2:$A$24,"NA",0,1) -> NA | L44: =_xlfn.XLOOKUP(Q44,Sheet1!$B$2:$B$24,Sheet1!$A$2:$A$24,"NA",0,1) -> NA | M44: =_xlfn.XLOOKUP(R44,Sheet1!$B$2:$B$24,Sheet1!$A$2:$A$24,"NA",0,1) -> NA | N44: =_xlfn.XLOOKUP(S44,Sheet1!$B$2:$B$24,Sheet1!$A$2:$A$24,"NA",0,1) -> NA
A45: S/C/M/164 | B45: 46045 | C45: CTS | D45: Report of the Meeting, Note by the Secretariat | E45: Other TrCMs | F45: Green Services Measures | G45: WTO Secretariat | H45: Informative/Neutral | I45: N/A | J45: =_xlfn.XLOOKUP(O45,Sheet1!$B$2:$B$24,Sheet1!$A$2:$A$24,"NA",0,1) -> NA | K45: =_xlfn.XLOOKUP(P45,Sheet1!$B$2:$B$24,Sheet1!$A$2:$A$24,"NA",0,1) -> NA | L45: =_xlfn.XLOOKUP(Q45,Sheet1!$B$2:$B$24,Sheet1!$A$2:$A$24,"NA",0,1) -> NA | M45: =_xlfn.XLOOKUP(R45,Sheet1!$B$2:$B$24,Sheet1!$A$2:$A$24,"NA",0,1) -> NA | N45: =_xlfn.XLOOKUP(S45,Sheet1!$B$2:$B$24,Sheet1!$A$2:$A$24,"NA",0,1) -> NA
A46: S/C/M/164 | B46: 46045 | C46: CTS | D46: Report of the Meeting, Note by the Secretariat | E46: Other TrCMs | F46: Green Services Measures | G46: European Union | H46: Supportive | I46: N/A | J46: =_xlfn.XLOOKUP(O46,Sheet1!$B$2:$B$24,Sheet1!$A$2:$A$24,"NA",0,1) -> NA | K46: =_xlfn.XLOOKUP(P46,Sheet1!$B$2:$B$24,Sheet1!$A$2:$A$24,"NA",0,1) -> NA | L46: =_xlfn.XLOOKUP(Q46,Sheet1!$B$2:$B$24,Sheet1!$A$2:$A$24,"NA",0,1) -> NA | M46: =_xlfn.XLOOKUP(R46,Sheet1!$B$2:$B$24,Sheet1!$A$2:$A$24,"NA",0,1) -> NA | N46: =_xlfn.XLOOKUP(S46,Sheet1!$B$2:$B$24,Sheet1!$A$2:$A$24,"NA",0,1) -> NA
A47: S/C/M/164 | B47: 46045 | C47: CTS | D47: Report of the Meeting, Note by the Secretariat | E47: Other TrCMs | F47: Green Services Measures | G47: China | H47: Supportive | I47: N/A | J47: =_xlfn.XLOOKUP(O47,Sheet1!$B$2:$B$24,Sheet1!$A$2:$A$24,"NA",0,1) -> NA | K47: =_xlfn.XLOOKUP(P47,Sheet1!$B$2:$B$24,Sheet1!$A$2:$A$24,"NA",0,1) -> NA | L47: =_xlfn.XLOOKUP(Q47,Sheet1!$B$2:$B$24,Sheet1!$A$2:$A$24,"NA",0,1) -> NA | M47: =_xlfn.XLOOKUP(R47,Sheet1!$B$2:$B$24,Sheet1!$A$2:$A$24,"NA",0,1) -> NA | N47: =_xlfn.XLOOKUP(S47,Sheet1!$B$2:$B$24,Sheet1!$A$2:$A$24,"NA",0,1) -> NA
A48: S/C/M/164 | B48: 46045 | C48: CTS | D48: Report of the Meeting, Note by the Secretariat | E48: Other TrCMs | F48: Green Services Measures | G48: Canada | H48: Supportive | I48: N/A | J48: =_xlfn.XLOOKUP(O48,Sheet1!$B$2:$B$24,Sheet1!$A$2:$A$24,"NA",0,1) -> NA | K48: =_xlfn.XLOOKUP(P48,Sheet1!$B$2:$B$24,Sheet1!$A$2:$A$24,"NA",0,1) -> NA | L48: =_xlfn.XLOOKUP(Q48,Sheet1!$B$2:$B$24,Sheet1!$A$2:$A$24,"NA",0,1) -> NA | M48: =_xlfn.XLOOKUP(R48,Sheet1!$B$2:$B$24,Sheet1!$A$2:$A$24,"NA",0,1) -> NA | N48: =_xlfn.XLOOKUP(S48,Sheet1!$B$2:$B$24,Sheet1!$A$2:$A$24,"NA",0,1) -> NA
A49: WT/COMTD/SE/13 | B49: 46076 | C49: COMTD | D49: REPORT OF THE COMMITTEE ON TRADE AND DEVELOPMENT, IN DEDICATED SESSION TO THE GENERAL COUNCIL | E49: Other TrCMs | F49: Green Industrial Policies | G49: WTO Secretariat | H49: Informative/Neutral | I49: N/A | J49: =_xlfn.XLOOKUP(O49,Sheet1!$B$2:$B$24,Sheet1!$A$2:$A$24,"NA",0,1) -> NA | K49: =_xlfn.XLOOKUP(P49,Sheet1!$B$2:$B$24,Sheet1!$A$2:$A$24,"NA",0,1) -> NA | L49: =_xlfn.XLOOKUP(Q49,Sheet1!$B$2:$B$24,Sheet1!$A$2:$A$24,"NA",0,1) -> NA | M49: =_xlfn.XLOOKUP(R49,Sheet1!$B$2:$B$24,Sheet1!$A$2:$A$24,"NA",0,1) -> NA | N49: =_xlfn.XLOOKUP(S49,Sheet1!$B$2:$B$24,Sheet1!$A$2:$A$24,"NA",0,1) -> NA
A50: WT/COMTD/SE/13 | B50: 46076 | C50: COMTD | D50: REPORT OF THE COMMITTEE ON TRADE AND DEVELOPMENT, IN DEDICATED SESSION TO THE GENERAL COUNCIL | E50: Other TrCMs | F50: Decarbonisation Measures | G50: WTO Secretariat | H50: Informative/Neutral | I50: N/A | J50: =_xlfn.XLOOKUP(O50,Sheet1!$B$2:$B$24,Sheet1!$A$2:$A$24,"NA",0,1) -> NA | K50: =_xlfn.XLOOKUP(P50,Sheet1!$B$2:$B$24,Sheet1!$A$2:$A$24,"NA",0,1) -> NA | L50: =_xlfn.XLOOKUP(Q50,Sheet1!$B$2:$B$24,Sheet1!$A$2:$A$24,"NA",0,1) -> NA | M50: =_xlfn.XLOOKUP(R50,Sheet1!$B$2:$B$24,Sheet1!$A$2:$A$24,"NA",0,1) -> NA | N50: =_xlfn.XLOOKUP(S50,Sheet1!$B$2:$B$24,Sheet1!$A$2:$A$24,"NA",0,1) -> NA
A51: WT/COMTD/SE/M/52 | B51: 46135 | C51: COMTD | D51: Note on the Meeting | E51: Other TrCMs | F51: Decarbonisation Measures | G51: ACP Group | H51: Supportive | I51: N/A | J51: =_xlfn.XLOOKUP(O51,Sheet1!$B$2:$B$24,Sheet1!$A$2:$A$24,"NA",0,1) -> NA | K51: =_xlfn.XLOOKUP(P51,Sheet1!$B$2:$B$24,Sheet1!$A$2:$A$24,"NA",0,1) -> NA | L51: =_xlfn.XLOOKUP(Q51,Sheet1!$B$2:$B$24,Sheet1!$A$2:$A$24,"NA",0,1) -> NA | M51: =_xlfn.XLOOKUP(R51,Sheet1!$B$2:$B$24,Sheet1!$A$2:$A$24,"NA",0,1) -> NA | N51: =_xlfn.XLOOKUP(S51,Sheet1!$B$2:$B$24,Sheet1!$A$2:$A$24,"NA",0,1) -> NA
... A63: WT/CTE/GEN/37/Rev.3 | B63: 46048 | C63: CTE | D63: CARBON BORDER ADJUSTMENT MECHANISM, COMMUNICATION FROM THE EUROPEAN UNION (Revision) | E63: Other TrCMs | F63: Temporary Decarbonisation Fund | G63: European Union | H63: Informative/Neutral | I63: N/A | J63: =_xlfn.XLOOKUP(O63,Sheet1!$B$2:$B$24,Sheet1!$A$2:$A$24,"NA",0,1) -> NA | K63: =_xlfn.XLOOKUP(P63,Sheet1!$B$2:$B$24,Sheet1!$A$2:$A$24,"NA",0,1) -> NA | L63: =_xlfn.XLOOKUP(Q63,Sheet1!$B$2:$B$24,Sheet1!$A$2:$A$24,"NA",0,1) -> NA | M63: =_xlfn.XLOOKUP(R63,Sheet1!$B$2:$B$24,Sheet1!$A$2:$A$24,"NA",0,1) -> NA | N63: =_xlfn.XLOOKUP(S63,Sheet1!$B$2:$B$24,Sheet1!$A$2:$A$24,"NA",0,1) -> NA
A64: WT/TPR/M/480/Add.1 | B64: 46059 | C64: TPR | D64: Trade Policy Review Thailand Minutes of the Meeting | E64: Carbon Measures | F64: Carbon Pricing Measures | G64: Singapore | H64: Recommendation/Request | I64: Mild | J64: =_xlfn.XLOOKUP(O64,Sheet1!$B$2:$B$24,Sheet1!$A$2:$A$24,"NA",0,1) -> WTO & Legal Concerns | K64: =_xlfn.XLOOKUP(P64,Sheet1!$B$2:$B$24,Sheet1!$A$2:$A$24,"NA",0,1) -> Regulatory Design & Methodology | L64: =_xlfn.XLOOKUP(Q64,Sheet1!$B$2:$B$24,Sheet1!$A$2:$A$24,"NA",0,1) -> NA | M64: =_xlfn.XLOOKUP(R64,Sheet1!$B$2:$B$24,Sheet1!$A$2:$A$24,"NA",0,1) -> NA | N64: =_xlfn.XLOOKUP(S64,Sheet1!$B$2:$B$24,Sheet1!$A$2:$A$24,"NA",0,1) -> NA | O64: Transparency | P64: Carbon Accounting Methodology
A65: WT/TPR/M/480/Add.1 | B65: 46059 | C65: TPR | D65: Trade Policy Review Thailand Minutes of the Meeting | E65: Carbon Measures | F65: Emissions Trading System (ETS) | G65: Singapore | H65: Recommendation/Request | I65: Mild | J65: =_xlfn.XLOOKUP(O65,Sheet1!$B$2:$B$24,Sheet1!$A$2:$A$24,"NA",0,1) -> WTO & Legal Concerns | K65: =_xlfn.XLOOKUP(P65,Sheet1!$B$2:$B$24,Sheet1!$A$2:$A$24,"NA",0,1) -> Regulatory Design & Methodology | L65: =_xlfn.XLOOKUP(Q65,Sheet1!$B$2:$B$24,Sheet1!$A$2:$A$24,"NA",0,1) -> NA | M65: =_xlfn.XLOOKUP(R65,Sheet1!$B$2:$B$24,Sheet1!$A$2:$A$24,"NA",0,1) -> NA | N65: =_xlfn.XLOOKUP(S65,Sheet1!$B$2:$B$24,Sheet1!$A$2:$A$24,"NA",0,1) -> NA | O65: Transparency | P65: Carbon Accounting Methodology
A66: WT/TPR/M/480/Add.1 | B66: 46059 | C66: TPR | D66: Trade Policy Review Thailand Minutes of the Meeting | E66: Carbon Measures | F66: CBAM-Type Mechanism | G66: Singapore | H66: Recommendation/Request | I66: Mild | J66: =_xlfn.XLOOKUP(O66,Sheet1!$B$2:$B$24,Sheet1!$A$2:$A$24,"NA",0,1) -> WTO & Legal Concerns | K66: =_xlfn.XLOOKUP(P66,Sheet1!$B$2:$B$24,Sheet1!$A$2:$A$24,"NA",0,1) -> WTO & Legal Concerns | L66: =_xlfn.XLOOKUP(Q66,Sheet1!$B$2:$B$24,Sheet1!$A$2:$A$24,"NA",0,1) -> Regulatory Design & Methodology | M66: =_xlfn.XLOOKUP(R66,Sheet1!$B$2:$B$24,Sheet1!$A$2:$A$24,"NA",0,1) -> NA | N66: =_xlfn.XLOOKUP(S66,Sheet1!$B$2:$B$24,Sheet1!$A$2:$A$24,"NA",0,1) -> NA | O66: Transparency | P66: WTO Compatibility | Q66: Carbon Accounting Methodology
A67: WT/MIN(26)/22/Add.2 | B67: 46100 | C67: MC/TESSD | D67: STATEMENT BY THE TESSD CO-CONVENORS (Addendum) | E67: Carbon Measures | F67: Carbon Pricing Measures | G67: TESSD Working Group | H67: Informative/Neutral | I67: N/A | J67: =_xlfn.XLOOKUP(O67,Sheet1!$B$2:$B$24,Sheet1!$A$2:$A$24,"NA",0,1) -> NA | K67: =_xlfn.XLOOKUP(P67,Sheet1!$B$2:$B$24,Sheet1!$A$2:$A$24,"NA",0,1) -> NA | L67: =_xlfn.XLOOKUP(Q67,Sheet1!$B$2:$B$24,Sheet1!$A$2:$A$24,"NA",0,1) -> NA | M67: =_xlfn.XLOOKUP(R67,Sheet1!$B$2:$B$24,Sheet1!$A$2:$A$24,"NA",0,1) -> NA | N67: =_xlfn.XLOOKUP(S67,Sheet1!$B$2:$B$24,Sheet1!$A$2:$A$24,"NA",0,1) -> NA
A68: WT/MIN(26)/22/Add.2 | B68: 46100 | C68: MC/TESSD | D68: STATEMENT BY THE TESSD CO-CONVENORS (Addendum) | E68: Carbon Measures | F68: Emissions Trading Systems (ETS) | G68: TESSD Working Group | H68: Informative/Neutral | I68: N/A | J68: =_xlfn.XLOOKUP(O68,Sheet1!$B$2:$B$24,Sheet1!$A$2:$A$24,"NA",0,1) -> NA | K68: =_xlfn.XLOOKUP(P68,Sheet1!$B$2:$B$24,Sheet1!$A$2:$A$24,"NA",0,1) -> NA | L68: =_xlfn.XLOOKUP(Q68,Sheet1!$B$2:$B$24,Sheet1!$A$2:$A$24,"NA",0,1) -> NA | M68: =_xlfn.XLOOKUP(R68,Sheet1!$B$2:$B$24,Sheet1!$A$2:$A$24,"NA",0,1) -> NA | N68: =_xlfn.XLOOKUP(S68,Sheet1!$B$2:$B$24,Sheet1!$A$2:$A$24,"NA",0,1) -> NA
A69: WT/MIN(26)/22/Add.2 | B69: 46100 | C69: MC/TESSD | D69: STATEMENT BY THE TESSD CO-CONVENORS (Addendum) | E69: Carbon Measures | F69: Border Carbon Adjustments (BCAs) | G69: TESSD Working Group | H69: Informative/Neutral | I69: N/A | J69: =_xlfn.XLOOKUP(O69,Sheet1!$B$2:$B$24,Sheet1!$A$2:$A$24,"NA",0,1) -> NA | K69: =_xlfn.XLOOKUP(P69,Sheet1!$B$2:$B$24,Sheet1!$A$2:$A$24,"NA",0,1) -> NA | L69: =_xlfn.XLOOKUP(Q69,Sheet1!$B$2:$B$24,Sheet1!$A$2:$A$24,"NA",0,1) -> NA | M69: =_xlfn.XLOOKUP(R69,Sheet1!$B$2:$B$24,Sheet1!$A$2:$A$24,"NA",0,1) -> NA | N69: =_xlfn.XLOOKUP(S69,Sheet1!$B$2:$B$24,Sheet1!$A$2:$A$24,"NA",0,1) -> NA
A70: WT/MIN(26)/22/Add.2 | B70: 46100 | C70: MC/TESSD | D70: STATEMENT BY THE TESSD CO-CONVENORS (Addendum) | E70: Other TrCMs | F70: Climate-Related Taxes | G70: TESSD Working Group | H70: Informative/Neutral | I70: N/A | J70: =_xlfn.XLOOKUP(O70,Sheet1!$B$2:$B$24,Sheet1!$A$2:$A$24,"NA",0,1) -> NA | K70: =_xlfn.XLOOKUP(P70,Sheet1!$B$2:$B$24,Sheet1!$A$2:$A$24,"NA",0,1) -> NA | L70: =_xlfn.XLOOKUP(Q70,Sheet1!$B$2:$B$24,Sheet1!$A$2:$A$24,"NA",0,1) -> NA | M70: =_xlfn.XLOOKUP(R70,Sheet1!$B$2:$B$24,Sheet1!$A$2:$A$24,"NA",0,1) -> NA | N70: =_xlfn.XLOOKUP(S70,Sheet1!$B$2:$B$24,Sheet1!$A$2:$A$24,"NA",0,1) -> NA
A71: WT/MIN(26)/22/Add.2 | B71: 46100 | C71: MC/TESSD | D71: STATEMENT BY THE TESSD CO-CONVENORS (Addendum) | E71: Other TrCMs | F71: Climate-Related Incentives | G71: TESSD Working Group | H71: Informative/Neutral | I71: N/A | J71: =_xlfn.XLOOKUP(O71,Sheet1!$B$2:$B$24,Sheet1!$A$2:$A$24,"NA",0,1) -> NA | K71: =_xlfn.XLOOKUP(P71,Sheet1!$B$2:$B$24,Sheet1!$A$2:$A$24,"NA",0,1) -> NA | L71: =_xlfn.XLOOKUP(Q71,Sheet1!$B$2:$B$24,Sheet1!$A$2:$A$24,"NA",0,1) -> NA | M71: =_xlfn.XLOOKUP(R71,Sheet1!$B$2:$B$24,Sheet1!$A$2:$A$24,"NA",0,1) -> NA | N71: =_xlfn.XLOOKUP(S71,Sheet1!$B$2:$B$24,Sheet1!$A$2:$A$24,"NA",0,1) -> NA
A72: WT/MIN(26)/22/Add.2 | B72: 46100 | C72: MC/TESSD | D72: STATEMENT BY THE TESSD CO-CONVENORS (Addendum) | E72: Sustainability & Environmental Requirements | F72: Sustainability Standards | G72: TESSD Working Group | H72: Informative/Neutral | I72: N/A | J72: =_xlfn.XLOOKUP(O72,Sheet1!$B$2:$B$24,Sheet1!$A$2:$A$24,"NA",0,1) -> NA | K72: =_xlfn.XLOOKUP(P72,Sheet1!$B$2:$B$24,Sheet1!$A$2:$A$24,"NA",0,1) -> NA | L72: =_xlfn.XLOOKUP(Q72,Sheet1!$B$2:$B$24,Sheet1!$A$2:$A$24,"NA",0,1) -> NA | M72: =_xlfn.XLOOKUP(R72,Sheet1!$B$2:$B$24,Sheet1!$A$2:$A$24,"NA",0,1) -> NA | N72: =_xlfn.XLOOKUP(S72,Sheet1!$B$2:$B$24,Sheet1!$A$2:$A$24,"NA",0,1) -> NA
A73: WT/MIN(26)/22/Add.2 | B73: 46100 | C73: MC/TESSD | D73: STATEMENT BY THE TESSD CO-CONVENORS (Addendum) | E73: Sustainability & Environmental Requirements | F73: Sustainability Certification Requirements | G73: TESSD Working Group | H73: Informative/Neutral | I73: N/A | J73: =_xlfn.XLOOKUP(O73,Sheet1!$B$2:$B$24,Sheet1!$A$2:$A$24,"NA",0,1) -> NA | K73: =_xlfn.XLOOKUP(P73,Sheet1!$B$2:$B$24,Sheet1!$A$2:$A$24,"NA",0,1) -> NA | L73: =_xlfn.XLOOKUP(Q73,Sheet1!$B$2:$B$24,Sheet1!$A$2:$A$24,"NA",0,1) -> NA | M73: =_xlfn.XLOOKUP(R73,Sheet1!$B$2:$B$24,Sheet1!$A$2:$A$24,"NA",0,1) -> NA | N73: =_xlfn.XLOOKUP(S73,Sheet1!$B$2:$B$24,Sheet1!$A$2:$A$24,"NA",0,1) -> NA
A74: WT/MIN(26)/22/Add.2 | B74: 46100 | C74: MC/TESSD | D74: STATEMENT BY THE TESSD CO-CONVENORS (Addendum) | E74: Sustainability & Environmental Requirements | F74: Sustainability Labelling Requirements | G74: TESSD Working Group | H74: Informative/Neutral | I74: N/A | J74: =_xlfn.XLOOKUP(O74,Sheet1!$B$2:$B$24,Sheet1!$A$2:$A$24,"NA",0,1) -> NA | K74: =_xlfn.XLOOKUP(P74,Sheet1!$B$2:$B$24,Sheet1!$A$2:$A$24,"NA",0,1) -> NA | L74: =_xlfn.XLOOKUP(Q74,Sheet1!$B$2:$B$24,Sheet1!$A$2:$A$24,"NA",0,1) -> NA | M74: =_xlfn.XLOOKUP(R74,Sheet1!$B$2:$B$24,Sheet1!$A$2:$A$24,"NA",0,1) -> NA | N74: =_xlfn.XLOOKUP(S74,Sheet1!$B$2:$B$24,Sheet1!$A$2:$A$24,"NA",0,1) -> NA
A75: WT/MIN(26)/22/Add.2 | B75: 46100 | C75: MC/TESSD | D75: STATEMENT BY THE TESSD CO-CONVENORS (Addendum) | E75: Other TrCMs | F75: Voluntary Climate Initiatives | G75: TESSD Working Group | H75: Informative/Neutral | I75: N/A | J75: =_xlfn.XLOOKUP(O75,Sheet1!$B$2:$B$24,Sheet1!$A$2:$A$24,"NA",0,1) -> NA | K75: =_xlfn.XLOOKUP(P75,Sheet1!$B$2:$B$24,Sheet1!$A$2:$A$24,"NA",0,1) -> NA | L75: =_xlfn.XLOOKUP(Q75,Sheet1!$B$2:$B$24,Sheet1!$A$2:$A$24,"NA",0,1) -> NA | M75: =_xlfn.XLOOKUP(R75,Sheet1!$B$2:$B$24,Sheet1!$A$2:$A$24,"NA",0,1) -> NA | N75: =_xlfn.XLOOKUP(S75,Sheet1!$B$2:$B$24,Sheet1!$A$2:$A$24,"NA",0,1) -> NA
A76: WT/MIN(26)/22/Add.2 | B76: 46100 | C76: MC/TESSD | D76: STATEMENT BY THE TESSD CO-CONVENORS (Addendum) | E76: Other TrCMs | F76: Sustainability-Linked Trade Preferences | G76: TESSD Working Group | H76: Informative/Neutral | I76: N/A | J76: =_xlfn.XLOOKUP(O76,Sheet1!$B$2:$B$24,Sheet1!$A$2:$A$24,"NA",0,1) -> NA | K76: =_xlfn.XLOOKUP(P76,Sheet1!$B$2:$B$24,Sheet1!$A$2:$A$24,"NA",0,1) -> NA | L76: =_xlfn.XLOOKUP(Q76,Sheet1!$B$2:$B$24,Sheet1!$A$2:$A$24,"NA",0,1) -> NA | M76: =_xlfn.XLOOKUP(R76,Sheet1!$B$2:$B$24,Sheet1!$A$2:$A$24,"NA",0,1) -> NA | N76: =_xlfn.XLOOKUP(S76,Sheet1!$B$2:$B$24,Sheet1!$A$2:$A$24,"NA",0,1) -> NA

Sheet Sheet1
A1: Concern Family Group | B1: Specific Concern
A2: WTO & Legal Concerns | B2: WTO Compatibility
A3: WTO & Legal Concerns | B3: National Treatment
A4: WTO & Legal Concerns | B4: MFN Concerns
A5: WTO & Legal Concerns | B5: Transparency
A6: WTO & Legal Concerns | B6: Unilateral Measures
A7: Development & Equity Concerns | B7: S&DT Concerns
A8: Development & Equity Concerns | B8: Development Impacts
A9: Development & Equity Concerns | B9: Capacity Constraints
A10: Development & Equity Concerns | B10: SME Impacts
A11: Trade Effects | B11: Trade Restrictiveness
A12: Trade Effects | B12: Discriminatory Effects
... A24: Governance & Regulatory Fragmentation | B24: Regulatory Fragmentation
